langchain_llm_streamer/__init__.py
langchain_llm_streamer/stream.py
langchain_llm_streamer-0.1.1.dist-info/METADATA
langchain_llm_streamer-0.1.1.dist-info/WHEEL
langchain_llm_streamer-0.1.1.dist-info/top_level.txt
langchain_llm_streamer-0.1.1.dist-info/RECORD
