Metadata-Version: 2.1
Name: langchain-llm-streamer
Version: 0.1.1
Summary: Stream and print responses from LangChain's language models asynchronously.
Author: Masachika Kamada
License: MIT
Project-URL: Homepage, https://github.com/masachika-kamada/langchain-llm-streamer
Requires-Python: >=3.7
